walt/__init__.py
walt/virtual/__init__.py
walt/virtual/node/__init__.py
walt/virtual/node/node.py
walt/virtual/node/udhcpc.py
walt/virtual/node/walt-vnode-ifdown
walt/virtual/node/walt-vnode-ifup
walt/virtual/setup/S52waltvirtualnode
walt/virtual/setup/__init__.py
walt/virtual/setup/node.py
walt_virtual-10.0.dist-info/METADATA
walt_virtual-10.0.dist-info/WHEEL
walt_virtual-10.0.dist-info/entry_points.txt
walt_virtual-10.0.dist-info/top_level.txt
walt_virtual-10.0.dist-info/RECORD
