Metadata-Version: 2.4
Name: walt-virtual
Version: 10.0
Summary: WalT components related to virtualization.
Home-page: https://walt-project.liglab.fr
Author: WalT developers
Author-email: walt-contact@univ-grenoble-alpes.fr
License: 3-Clause BSD
Keywords: WalT testbed
Requires-Dist: walt-common==10.0
Dynamic: author
Dynamic: author-email
Dynamic: home-page
Dynamic: keywords
Dynamic: license
Dynamic: requires-dist
Dynamic: summary
